{
  "manual" : false,
  "urls" : {
    "877312163" : {
      "success" : {
        "timestamp" : "2024-09-04T19:23:07.488825692Z"
      }
    },
    "1503649481" : {
      "success" : {
        "timestamp" : "2024-09-04T19:23:07.703540810Z"
      }
    },
    "-659794267" : {
      "success" : {
        "timestamp" : "2024-09-04T19:23:07.903547021Z"
      }
    },
    "1640937235" : {
      "success" : {
        "timestamp" : "2024-09-04T19:23:08.174388889Z"
      }
    },
    "1162652855" : {
      "success" : {
        "timestamp" : "2024-09-04T19:23:08.436650454Z"
      }
    }
  }
}