{
  "manual" : false,
  "urls" : {
    "643208889" : {
      "success" : {
        "timestamp" : "2024-09-04T17:45:27.060390463Z"
      }
    },
    "-1029619299" : {
      "success" : {
        "timestamp" : "2024-09-04T17:45:37.284986644Z"
      }
    },
    "-1292556948" : {
      "success" : {
        "timestamp" : "2024-09-04T17:45:37.915682392Z"
      }
    },
    "-1988725240" : {
      "success" : {
        "timestamp" : "2024-09-04T17:45:45.460346888Z"
      }
    },
    "-85852404" : {
      "success" : {
        "timestamp" : "2024-09-04T17:45:53.527115244Z"
      }
    },
    "-1986828376" : {
      "success" : {
        "timestamp" : "2024-09-04T17:46:01.403086586Z"
      }
    }
  }
}