{
  "manual" : false,
  "urls" : {
    "-1669125095" : {
      "success" : {
        "timestamp" : "2024-09-04T17:48:13.497141908Z"
      }
    },
    "1610481405" : {
      "success" : {
        "timestamp" : "2024-09-04T17:48:23.470864131Z"
      }
    },
    "506391564" : {
      "success" : {
        "timestamp" : "2024-09-04T17:48:24.307415430Z"
      }
    },
    "223941800" : {
      "success" : {
        "timestamp" : "2024-09-04T17:48:32.326816458Z"
      }
    },
    "152890796" : {
      "success" : {
        "timestamp" : "2024-09-04T17:48:32.841439608Z"
      }
    },
    "-187879864" : {
      "success" : {
        "timestamp" : "2024-09-04T17:48:33.363818607Z"
      }
    }
  }
}